multisplitby/__init__.py
multisplitby-0.0.1.dist-info/LICENSE
multisplitby-0.0.1.dist-info/METADATA
multisplitby-0.0.1.dist-info/WHEEL
multisplitby-0.0.1.dist-info/top_level.txt
multisplitby-0.0.1.dist-info/zip-safe
multisplitby-0.0.1.dist-info/RECORD
