Metadata-Version: 2.1
Name: multisplitby
Version: 0.0.1
Summary: Split an iterable into multiple using arbitrary predicates.
Home-page: https://github.com/cthoyt/multisplitby
Author: Charles Tapley Hoyt
Author-email: cthoyt@gmail.com
Maintainer: Charles Tapley Hoyt
Maintainer-email: cthoyt@gmail.com
License: MIT
Download-URL: https://github.com/cthoyt/multisplitby/releases
Project-URL: Bug Tracker, https://github.com/cthoyt/multisplitby/issues
Project-URL: Source Code, https://github.com/cthoyt/multisplitby
Keywords: iteration
Platform: UNKNOWN
Classifier: Development Status :: 1 - Planning
Classifier: Intended Audience :: Developers
Classifier: License :: OSI Approved :: MIT License
Classifier: Operating System :: OS Independent
Classifier: Programming Language :: Python
Classifier: Programming Language :: Python :: 3.5
Classifier: Programming Language :: Python :: 3.6
Classifier: Programming Language :: Python :: 3.7
Classifier: Programming Language :: Python :: 3 :: Only
Requires-Python: >=3.5
